src/README.md
src/__init__.py
src/analyzers/__init__.py
src/analyzers/advanced_functionality_detector.py
src/analyzers/ai_group_analyzer.py
src/analyzers/ai_insights_analyzer.py
src/analyzers/ai_insights_analyzer_lightweight.py
src/analyzers/analysis_cache.py
src/analyzers/code_quality_analyzer.py
src/analyzers/completeness_verifier.py
src/analyzers/connection_analyzer.py
src/analyzers/dependency_graph.py
src/analyzers/file_analyzer.py
src/analyzers/functionality_analyzer.py
src/analyzers/functionality_detector.py
src/analyzers/madge_analyzer.py
src/analyzers/project_analyzer.py
src/analyzers/project_progress_tracker.py
src/analyzers/project_scanner.py
src/analyzers/project_structure_analyzer.py
src/analyzers/rules_suggester.py
src/analyzers/smart_dependency_analyzer.py
src/analyzers/structured_rules_suggester.py
src/analyzers/testability_analyzer.py
src/commands/analyze_group.py
src/commands/generate_suggestions.py
src/commands/rules_commands.py
src/commands/track_progress.py
src/commands/track_progress_clean.py
src/core/__init__.py
src/core/analyze_and_suggest.py
src/core/analyze_project_with_anthropic.py
src/core/analyze_with_anthropic_direct.py
src/core/analyze_with_anthropic_simple.py
src/core/project_analyzer.py
src/core/project_prompt.py
src/core/project_prompt_cli.py
src/factory.py
src/generators/__init__.py
src/generators/branch_strategy_generator.py
src/generators/contextual_prompt_generator.py
src/generators/implementation_prompt_generator.py
src/generators/implementation_prompt_generator_simple.py
src/generators/implementation_proposal_generator.py
src/generators/markdown_generator.py
src/generators/prompt_generator.py
src/generators/rules_report_generator.py
src/generators/templates/project_report.md
src/integrations/__init__.py
src/integrations/anthropic.py
src/integrations/anthropic_advanced.py
src/integrations/anthropic_rules_analyzer.py
src/integrations/copilot.py
src/integrations/copilot_advanced.py
src/integrations/openai_integration.py
projectprompt-1.3.2.dist-info/METADATA
projectprompt-1.3.2.dist-info/WHEEL
projectprompt-1.3.2.dist-info/entry_points.txt
projectprompt-1.3.2.dist-info/RECORD
