Metadata-Version: 2.3
Name: projectprompt
Version: 1.3.2
Summary: Intelligent assistant for project analysis and documentation using AI
License: MIT
Keywords: ai,prompt-engineering,documentation,project-analysis
Author: Daniel Lagowski Solé
Author-email: daniel@lagowski.es
Requires-Python: >=3.8,<4.0
Classifier: Development Status :: 5 - Production/Stable
Classifier: Environment :: Console
Classifier: Intended Audience :: Developers
Classifier: License :: OSI Approved :: MIT License
Classifier: Programming Language :: Python :: 3
Classifier: Programming Language :: Python :: 3.8
Classifier: Programming Language :: Python :: 3.9
Classifier: Programming Language :: Python :: 3.10
Classifier: Programming Language :: Python :: 3.11
Classifier: Programming Language :: Python :: 3.12
Classifier: Programming Language :: Python :: 3.13
Classifier: Topic :: Software Development :: Documentation
Classifier: Topic :: Software Development :: Libraries :: Python Modules
Requires-Dist: anthropic (>=0.5.0,<0.6.0)
Requires-Dist: click (>=8.1.7,<9.0.0)
Requires-Dist: jinja2 (>=3.0.0,<4.0.0)
Requires-Dist: keyring (>=24.0.0,<25.0.0)
Requires-Dist: openai (>=1.50.0)
Requires-Dist: python-frontmatter (>=1.0.0,<2.0.0)
Requires-Dist: pyyaml (>=6.0.1,<7.0.0)
Requires-Dist: requests (>=2.28.0,<3.0.0)
Requires-Dist: rich (>=13.5.0)
Requires-Dist: setuptools (>=69.0.0,<70.0.0)
Requires-Dist: tabulate (>=0.9.0,<0.10.0)
Requires-Dist: tiktoken (>=0.5.0)
Requires-Dist: typer (==0.9.0)
Project-URL: Documentation, https://github.com/Dixter999/project-prompt?tab=readme-ov-file#
Project-URL: Repository, https://github.com/Dixter999/project-prompt
